<Properties StartupConfiguration="{A73D3BE9-A1B7-409D-9190-4145177687DA}|Default">
  <MonoDevelop.Ide.ItemProperties.Personality__Quiz__list.iOS PreferredExecutionTarget="MonoDevelop.IPhone.IPhoneSimulatorTarget.E19D1629-F87B-4B04-B7DA-51618009749D" />
  <MonoDevelop.Ide.Workbench>
    <Pads>
      <Pad Id="ProjectPad">
        <State name="__root__">
          <Node name="Personality_Quiz_list" expanded="True">
            <Node name="Personality_Quiz_list" expanded="True">
              <Node name="Data" expanded="True" />
              <Node name="App.xaml" expanded="True" />
              <Node name="MainPage.xaml" expanded="True" selected="True" />
              <Node name="Results.xaml" expanded="True" />
            </Node>
          </Node>
        </State>
      </Pad>
    </Pads>
  </MonoDevelop.Ide.Workbench>
  <MonoDevelop.Ide.ItemProperties.Personality__Quiz__list.Android PreferredExecutionTarget="Android.SelectDevice" />
  <MonoDevelop.Ide.DebuggingService.PinnedWatches />
  <MonoDevelop.Ide.Workspace ActiveConfiguration="Debug" />
  <MonoDevelop.Ide.DebuggingService.Breakpoints>
    <BreakpointStore />
  </MonoDevelop.Ide.DebuggingService.Breakpoints>
  <MultiItemStartupConfigurations />
</Properties>